pytterns/__init__.py
pytterns/_version.py
pytterns/patterns.py
pytterns/core/__init__.py
pytterns/core/decorators.py
pytterns/core/loaders.py
pytterns-0.1.5.dist-info/licenses/AUTHORS
pytterns-0.1.5.dist-info/licenses/LICENCE
pytterns-0.1.5.dist-info/METADATA
pytterns-0.1.5.dist-info/WHEEL
pytterns-0.1.5.dist-info/top_level.txt
pytterns-0.1.5.dist-info/RECORD
