Metadata-Version: 2.4
Name: pytterns
Version: 0.1.5
Summary: A library to easily use design patterns with Python
Author: Marcos Rosa
Author-email: Marcos Rosa <marcos.cantor@gmail.com>
License: MIT
Classifier: Programming Language :: Python :: 3
Classifier: License :: OSI Approved :: MIT License
Classifier: Operating System :: OS Independent
Requires-Python: >=3.6
License-File: LICENCE
License-File: AUTHORS
Provides-Extra: dev
Requires-Dist: pytest; extra == "dev"
Dynamic: author
Dynamic: license-file
Dynamic: requires-python
